Proyecto/pwm_peripheral.v
// ======================================================
// Módulo PWM para RISC-V con bus paralelo
// Características:
// - Configuración de frecuencia (divisor)
// - Duty cycle ajustable (0-100%)
// - Tres modos de alineación: izquierda, centro, derecha
// ======================================================
`timescale 1ns / 1ps

module pwm_peripheral (
    input            clk,
    input            rst,
    input     [31:0] add,
    input     [31:0] din,
    output reg [31:0] dout,
    input            wr,
    input            rd,
    output reg       wr_busy,
    output reg       rd_busy,
    input            wr_strobe,
    input            rd_strobe,
    input      [3:0] mask,
    output reg       pwm_out  // Salida PWM añadida
);

    // Direcciones de registros
    parameter BASE_ADDR = 32'h4000_0000;
    parameter REG_DIV   = 32'h0000_0000;
    parameter REG_DUTY  = 32'h0000_0004;
    parameter REG_CTRL  = 32'h0000_0008;

    // Registros de configuración
    reg [31:0] div_counter;
    reg [31:0] duty_cycle;
    reg [1:0]  pwm_align;
    reg        pwm_enable;
    
    // Registros sombra
    reg [31:0] div_counter_shadow;
    reg [31:0] duty_cycle_shadow;
    reg [1:0]  pwm_align_shadow;
    reg        pwm_enable_shadow;
    reg        update_pending;

    // Generación PWM
    reg [31:0] pwm_counter;
    wire       pwm_tick;
    reg [31:0] safe_duty_cycle;

    // Máquina de estados
    localparam [2:0] 
        IDLE        = 3'b000,
        WRITE_START = 3'b001,
        WRITE_HOLD  = 3'b010,
        READ_START  = 3'b011,
        READ_HOLD   = 3'b100,
        UPDATE_REG  = 3'b101;
    
    reg [2:0] state, next_state;

    // Lógica de actualización
    always @(posedge clk or posedge rst) begin
        if (rst) begin
            state <= IDLE;
            div_counter  <= 32'd100;
            duty_cycle   <= 32'd50;
            pwm_align    <= 2'b00;
            pwm_enable   <= 1'b1;
            safe_duty_cycle <= 50;
            wr_busy <= 0;
            rd_busy <= 0;
            dout <= 0;
            update_pending <= 0;
            pwm_out <= 0;
        end else begin
            state <= next_state;
            
            // Actualización directa en UPDATE_REG
            if (state == UPDATE_REG) begin
                div_counter <= div_counter_shadow;
                duty_cycle <= duty_cycle_shadow;
                pwm_align <= pwm_align_shadow;
                pwm_enable <= pwm_enable_shadow;
                safe_duty_cycle <= (duty_cycle_shadow > 100) ? 100 : 
                                  (duty_cycle_shadow < 0) ? 0 : duty_cycle_shadow[31:0];
            end
        end
    end

    // Máquina de estados del bus
    always @(*) begin
        next_state = state;
        wr_busy = 0;
        rd_busy = 0;
        
        case (state)
            IDLE: begin
                if (wr && ((add == BASE_ADDR + REG_DIV) || 
                          (add == BASE_ADDR + REG_DUTY) || 
                          (add == BASE_ADDR + REG_CTRL))) begin
                    next_state = WRITE_START;
                end
                else if (rd && ((add == BASE_ADDR + REG_DIV) || 
                               (add == BASE_ADDR + REG_DUTY) || 
                               (add == BASE_ADDR + REG_CTRL))) begin
                    next_state = READ_START;
                end
            end
            
            WRITE_START: begin
                wr_busy = 1;
                if (wr_strobe) next_state = UPDATE_REG;
                else next_state = WRITE_HOLD;
            end
            
            WRITE_HOLD: begin
                wr_busy = 1;
                if (wr_strobe) next_state = UPDATE_REG;
            end
            
            READ_START: begin
                rd_busy = 1;
                next_state = READ_HOLD;
            end
            
            READ_HOLD: begin
                rd_busy = 1;
                if (rd_strobe) next_state = IDLE;
            end
            
            UPDATE_REG: begin
                next_state = IDLE;
            end
        endcase
    end

    // Escritura de registros
    always @(posedge clk) begin
        if (rst) begin
            div_counter_shadow  <= 32'd100;
            duty_cycle_shadow   <= 32'd50;
            pwm_align_shadow    <= 2'b00;
            pwm_enable_shadow   <= 1'b1;
            update_pending <= 0;
        end else if (state == WRITE_START) begin
            case (add)
                BASE_ADDR + REG_DIV:  div_counter_shadow <= din;
                BASE_ADDR + REG_DUTY: duty_cycle_shadow  <= din;
                BASE_ADDR + REG_CTRL: begin
                    pwm_align_shadow  <= din[1:0];
                    pwm_enable_shadow <= din[31];
                end
            endcase
            update_pending <= 1;
        end
    end

    // Lectura de registros
    always @(negedge clk) begin
        if (state == READ_START) begin
            case (add)
                BASE_ADDR + REG_DIV:  dout <= div_counter;
                BASE_ADDR + REG_DUTY: dout <= duty_cycle;
                BASE_ADDR + REG_CTRL: dout <= {29'b0, pwm_align, pwm_enable};
                default: dout <= 32'hDEAD_BEEF;
            endcase
        end
    end

    // Generación de señal PWM
    assign pwm_tick = (pwm_counter == div_counter);

    // Cálculo de umbrales para cada alineación
    wire [31:0] rising_threshold, falling_threshold;
    assign rising_threshold = (pwm_align == 2'b00) ? 0 :                           // Izquierda
                             (pwm_align == 2'b01) ? (div_counter/2) - (div_counter*safe_duty_cycle/200) :  // Centro
                             div_counter - (div_counter*safe_duty_cycle/100);      // Derecha

    assign falling_threshold = (pwm_align == 2'b00) ? (div_counter*safe_duty_cycle/100) :  // Izquierda
                              (pwm_align == 2'b01) ? (div_counter/2) + (div_counter*safe_duty_cycle/200) : // Centro
                              div_counter;                                           // Derecha

    always @(posedge clk or posedge rst) begin
        if (rst) begin
            pwm_out <= 0;
            pwm_counter <= 0;
        end else begin
            if (pwm_counter >= div_counter) begin
                pwm_counter <= 0;
            end else begin
                pwm_counter <= pwm_counter + 1;
            end
            
            if (pwm_enable) begin
                if ((pwm_counter >= rising_threshold) && 
                    (pwm_counter < falling_threshold)) begin
                    pwm_out <= 1;
                end else begin
                    pwm_out <= 0;
                end
            end else begin
                pwm_out <= 0;
            end
        end
    end

    // Monitorización para GTKWave
    // synthesis translate_off
    always @(posedge clk) begin
        if (state == WRITE_START) begin
            $display("[%0t] WRITE: Addr=0x%h Data=0x%h", $time, add, din);
        end
        else if (state == READ_START) begin
            $display("[%0t] READ: Addr=0x%h Data=0x%h", $time, add, dout);
        end
        
        if (pwm_tick) begin
            $display("[%0t] PWM: Period | FreqDiv=%0d Duty=%0d%% Align=%s Out=%b", 
                    $time, div_counter, safe_duty_cycle, 
                    pwm_align == 2'b00 ? "Left" : 
                    pwm_align == 2'b01 ? "Center" : "Right",
                    pwm_out);
        end
    end
    // synthesis translate_on

endmodule

Proyecto/pwm_peripheral_tb.v
// ======================================================
// Testbench COMPLETO para PWM Peripheral (CORREGIDO)
// ======================================================
`timescale 1ns / 1ps

module pwm_peripheral_tb;

    // Parámetros de simulación
    localparam CLK_PERIOD = 10;  // 100 MHz
    localparam BASE_ADDR = 32'h4000_0000;

    // Señales del bus
    reg        clk;
    reg        rst;
    reg [31:0] add;
    reg [31:0] din;
    wire [31:0] dout;
    reg        wr;
    reg        rd;
    wire       wr_busy;
    wire       rd_busy;
    reg        wr_strobe;
    reg        rd_strobe;
    reg [3:0]  mask;
    wire       pwm_out;

    // Instancia del PWM
    pwm_peripheral uut (
        .clk(clk), .rst(rst), .add(add), .din(din), .dout(dout),
        .wr(wr), .rd(rd), .wr_busy(wr_busy), .rd_busy(rd_busy),
        .wr_strobe(wr_strobe), .rd_strobe(rd_strobe), .mask(mask),
        .pwm_out(pwm_out)
    );

    // Generación de reloj
    initial begin
        clk = 1;
        forever #(CLK_PERIOD/2) clk = ~clk;
    end

    // Tarea para escritura de registros
    task write_reg(input [31:0] address, input [31:0] data);
        begin
            @(posedge clk);
            add = address;
            din = data;
            wr = 1;
            @(posedge clk);
            wr = 0;
            #(CLK_PERIOD*2) wr_strobe = 1;
            @(posedge clk);
            wr_strobe = 0;
            #(CLK_PERIOD*10);
            $display("[%0t] WRITE: Addr=0x%h Data=0x%h", $time, address, data);
        end
    endtask

    // Tarea para lectura de registros
    task read_reg(input [31:0] address);
        begin
            @(posedge clk);
            add = address;
            rd = 1;
            @(posedge clk);
            rd = 0;
            #(CLK_PERIOD*2) rd_strobe = 1;
            @(posedge clk);
            rd_strobe = 0;
            #(CLK_PERIOD*2);
            $display("[%0t] READ: Addr=0x%h Data=0x%h", $time, address, dout);
        end
    endtask

    // Secuencia de pruebas CORREGIDA
    initial begin
        // Inicialización
        rst = 1;
        add = 0;
        din = 0;
        wr = 0;
        rd = 0;
        wr_strobe = 0;
        rd_strobe = 0;
        mask = 4'b1111;
        
        // Configuración de dumpfile para GTKWave
        $dumpfile("pwm_wave.vcd");
        $dumpvars(0, pwm_peripheral_tb);
        
        // Reset inicial
        #(CLK_PERIOD*2) rst = 0;
        
        // ---------------------------------------------------------------------
        // Prueba 1: Comportamiento normal con diferentes alineaciones
        // ---------------------------------------------------------------------
        $display("\n=== PRUEBA 1: Comportamiento normal ===");
        
        // Configuración inicial
        write_reg(BASE_ADDR + 32'h0000, 32'd100);  // div_counter = 100
        
        // Caso 1.1: Alineación izquierda (HABILITAR PWM: bit 31 = 1)
        $display("\nCaso 1.1: Alineación izquierda");
        write_reg(BASE_ADDR + 32'h0008, 32'h80000000);  // ¡Enable + Alineación izquierda!
        write_reg(BASE_ADDR + 32'h0004, 32'd25);        // Duty 25%
        #(CLK_PERIOD * 500);
        
        write_reg(BASE_ADDR + 32'h0004, 32'd75);        // Duty 75%
        #(CLK_PERIOD * 500);
        
        // Caso 1.2: Alineación centrada (HABILITAR PWM: bit 31 = 1)
        $display("\nCaso 1.2: Alineación centrada");
        write_reg(BASE_ADDR + 32'h0008, 32'h80000001);  // ¡Enable + Alineación centro!
        write_reg(BASE_ADDR + 32'h0004, 32'd30);        // Duty 30%
        #(CLK_PERIOD * 500);
        
        write_reg(BASE_ADDR + 32'h0004, 32'd70);        // Duty 70%
        #(CLK_PERIOD * 500);
        
        // Caso 1.3: Alineación derecha (HABILITAR PWM: bit 31 = 1)
        $display("\nCaso 1.3: Alineación derecha");
        write_reg(BASE_ADDR + 32'h0008, 32'h80000002);  // ¡Enable + Alineación derecha!
        write_reg(BASE_ADDR + 32'h0004, 32'd10);        // Duty 10%
        #(CLK_PERIOD * 500);
        
        write_reg(BASE_ADDR + 32'h0004, 32'd90);        // Duty 90%
        #(CLK_PERIOD * 500);
        
        // ---------------------------------------------------------------------
        // Prueba 2: Casos límite (TODOS CON PWM HABILITADO)
        // ---------------------------------------------------------------------
        $display("\n=== PRUEBA 2: Casos límite ===");
        
        // Caso 2.1: Duty cycle 0% y 100%
        $display("\nCaso 2.1: Duty 0%% y 100%%");
        write_reg(BASE_ADDR + 32'h0004, 32'd0);         // 0% duty
        #(CLK_PERIOD * 300);
        write_reg(BASE_ADDR + 32'h0004, 32'd100);       // 100% duty
        #(CLK_PERIOD * 300);
        
        // Caso 2.2: Duty cycle >100%
        $display("\nCaso 2.2: Duty 150%% (debe limitarse a 100%%)");
        write_reg(BASE_ADDR + 32'h0004, 32'd150);       // 150% duty
        #(CLK_PERIOD * 300);
        
        // Caso 2.3: Cambio dinámico de alineación (HABILITAR PWM EN TODOS)
        $display("\nCaso 2.3: Cambio dinámico de alineación");
        write_reg(BASE_ADDR + 32'h0008, 32'h80000000);  // Enable + Izquierda
        #(CLK_PERIOD * 200);
        write_reg(BASE_ADDR + 32'h0008, 32'h80000001);  // Enable + Centro
        #(CLK_PERIOD * 200);
        write_reg(BASE_ADDR + 32'h0008, 32'h80000002);  // Enable + Derecha
        #(CLK_PERIOD * 200);
        
        // Caso 2.4: Divisor de frecuencia mínimo/máximo
        $display("\nCaso 2.4: Divisor mínimo (2) y máximo (65535)");
        write_reg(BASE_ADDR + 32'h0000, 32'd2);         // Divisor mínimo
        #(CLK_PERIOD * 50);
        write_reg(BASE_ADDR + 32'h0000, 32'h0000FFFF);  // Divisor máximo
        #(CLK_PERIOD * 50);
        
        // Caso 2.5: Escritura simultánea (YA TIENE ENABLE)
        $display("\nCaso 2.5: Escritura simultánea");
        write_reg(BASE_ADDR + 32'h0000, 32'd100);       // Restaurar divisor
        write_reg(BASE_ADDR + 32'h0004, 32'd50);        // Duty 50%
        // Ya incluye enable (bit 31=1)
        write_reg(BASE_ADDR + 32'h0008, 32'h80000001);  // Enable + alineación centro
        #(CLK_PERIOD * 300);
        
        // ---------------------------------------------------------------------
        // Verificación final
        // ---------------------------------------------------------------------
        $display("\n=== Verificación final ===");
        read_reg(BASE_ADDR + 32'h0000);  // Leer divisor
        read_reg(BASE_ADDR + 32'h0004);  // Leer duty cycle
        read_reg(BASE_ADDR + 32'h0008);  // Leer registro de control
        
        // Finalizar simulación
        #(CLK_PERIOD * 100);
        $display("\nSimulación completada exitosamente");
        $finish;
    end

    // Monitorización adicional
    always @(posedge clk) begin
        if (uut.pwm_tick) begin
            $display("[%0t] PWM: Counter=%0d, Out=%b, Duty=%0d%%, Align=%s", 
                    $time, uut.pwm_counter, pwm_out, 
                    uut.safe_duty_cycle,
                    uut.pwm_align == 2'b00 ? "Left" : 
                    uut.pwm_align == 2'b01 ? "Center" : "Right");
        end
    end

endmodule

Proyecto/pwm_wave.vcd
$date
	Fri Jul 18 14:11:42 2025
$end
$version
	Icarus Verilog
$end
$timescale
	1ps
$end
$scope module pwm_peripheral_tb $end
$var wire 1 ! wr_busy $end
$var wire 1 " rd_busy $end
$var wire 1 # pwm_out $end
$var wire 32 $ dout [31:0] $end
$var parameter 32 % BASE_ADDR $end
$var parameter 32 & CLK_PERIOD $end
$var reg 32 ' add [31:0] $end
$var reg 1 ( clk $end
$var reg 32 ) din [31:0] $end
$var reg 4 * mask [3:0] $end
$var reg 1 + rd $end
$var reg 1 , rd_strobe $end
$var reg 1 - rst $end
$var reg 1 . wr $end
$var reg 1 / wr_strobe $end
$scope module uut $end
$var wire 32 0 add [31:0] $end
$var wire 1 ( clk $end
$var wire 32 1 din [31:0] $end
$var wire 4 2 mask [3:0] $end
$var wire 1 + rd $end
$var wire 1 , rd_strobe $end
$var wire 1 - rst $end
$var wire 1 . wr $end
$var wire 1 / wr_strobe $end
$var wire 32 3 rising_threshold [31:0] $end
$var wire 1 4 pwm_tick $end
$var wire 32 5 falling_threshold [31:0] $end
$var parameter 32 6 BASE_ADDR $end
$var parameter 3 7 IDLE $end
$var parameter 3 8 READ_HOLD $end
$var parameter 3 9 READ_START $end
$var parameter 32 : REG_CTRL $end
$var parameter 32 ; REG_DIV $end
$var parameter 32 < REG_DUTY $end
$var parameter 3 = UPDATE_REG $end
$var parameter 3 > WRITE_HOLD $end
$var parameter 3 ? WRITE_START $end
$var reg 32 @ div_counter [31:0] $end
$var reg 32 A div_counter_shadow [31:0] $end
$var reg 32 B dout [31:0] $end
$var reg 32 C duty_cycle [31:0] $end
$var reg 32 D duty_cycle_shadow [31:0] $end
$var reg 3 E next_state [2:0] $end
$var reg 2 F pwm_align [1:0] $end
$var reg 2 G pwm_align_shadow [1:0] $end
$var reg 32 H pwm_counter [31:0] $end
$var reg 1 I pwm_enable $end
$var reg 1 J pwm_enable_shadow $end
$var reg 1 # pwm_out $end
$var reg 1 " rd_busy $end
$var reg 32 K safe_duty_cycle [31:0] $end
$var reg 3 L state [2:0] $end
$var reg 1 M update_pending $end
$var reg 1 ! wr_busy $end
$upscope $end
$scope task read_reg $end
$var reg 32 N address [31:0] $end
$upscope $end
$scope task write_reg $end
$var reg 32 O address [31:0] $end
$var reg 32 P data [31:0] $end
$upscope $end
$upscope $end
$enddefinitions $end
$comment Show the parameter values. $end
$dumpall
b1 ?
b10 >
b101 =
b100 <
b0 ;
b1000 :
b11 9
b100 8
b0 7
b1000000000000000000000000000000 6
b1010 &
b1000000000000000000000000000000 %
$end
#0
$dumpvars
bx P
bx O
bx N
0M
b0 L
b110010 K
1J
1I
b0 H
b0 G
b0 F
b0 E
b110010 D
b110010 C
b0 B
b1100100 A
b1100100 @
b110010 5
04
b0 3
b1111 2
b0 1
b0 0
0/
0.
1-
0,
0+
b1111 *
b0 )
1(
b0 '
b0 $
0#
0"
0!
$end
#5000
0(
#10000
1(
#15000
0(
#20000
1#
b1 H
b1 E
1.
b1100100 )
b1100100 1
b1000000000000000000000000000000 '
b1000000000000000000000000000000 0
1(
b1100100 P
b1000000000000000000000000000000 O
0-
#25000
0(
#30000
1!
b10 H
b1 L
b10 E
0.
1(
#35000
0(
#40000
1!
b10 L
b11 H
1M
1(
#45000
0(
#50000
b100 H
b101 L
b0 E
0!
1(
0/
#55000
0(
#60000
b0 L
b101 H
1(
#65000
0(
#70000
b110 H
1(
#75000
0(
#80000
b111 H
1(
#85000
0(
#90000
b1000 H
1(
#95000
0(
#100000
b1001 H
1(
#105000
0(
#110000
b1010 H
1(
#115000
0(
#120000
b1011 H
1(
#125000
0(
#130000
b1100 H
1(
#135000
0(
#140000
b1101 H
1(
#145000
0(
#150000
b1110 H
b1 E
1.
b10000000000000000000000000000000 )
b10000000000000000000000000000000 1
b1000000000000000000000000001000 '
b1000000000000000000000000001000 0
1(
b10000000000000000000000000000000 P
b1000000000000000000000000001000 O
#155000
0(
#160000
1!
b1 L
b1111 H
b10 E
0.
1(
#165000
0(
#170000
1!
b10000 H
b10 L
1(
#175000
0(
#180000
b101 L
b10001 H
b0 E
0!
1(
0/
#185000
0(
#190000
b10010 H
b0 L
1(
#195000
0(
#200000
b10011 H
1(
#205000
0(
#210000
b10100 H
1(
#215000
0(
#220000
b10101 H
1(
#225000
0(
#230000
b10110 H
1(
#235000
0(
#240000
b10111 H
1(
#245000
0(
#250000
b11000 H
1(
#255000
0(
#260000
b11001 H
1(
#265000
0(
#270000
b11010 H
1(
#275000
0(
#280000
b11011 H
b1 E
1.
b11001 )
b11001 1
b1000000000000000000000000000100 '
b1000000000000000000000000000100 0
1(
b11001 P
b1000000000000000000000000000100 O
#285000
0(
#290000
1!
b11100 H
b1 L
b10 E
0.
1(
#295000
0(
#300000
1!
b10 L
b11101 H
b11001 D
1(
#305000
0(
#310000
b11110 H
b101 L
b0 E
0!
1(
0/
#315000
0(
#320000
b11001 5
b11001 K
b11001 C
b0 L
b11111 H
1(
#325000
0(
#330000
0#
b100000 H
1(
#335000
0(
#340000
b100001 H
1(
#345000
0(
#350000
b100010 H
1(
#355000
0(
#360000
b100011 H
1(
#365000
0(
#370000
b100100 H
1(
#375000
0(
#380000
b100101 H
1(
#385000
0(
#390000
b100110 H
1(
#395000
0(
#400000
b100111 H
1(
#405000
0(
#410000
b101000 H
1(
#415000
0(
#420000
b101001 H
1(
#425000
0(
#430000
b101010 H
1(
#435000
0(
#440000
b101011 H
1(
#445000
0(
#450000
b101100 H
1(
#455000
0(
#460000
b101101 H
1(
#465000
0(
#470000
b101110 H
1(
#475000
0(
#480000
b101111 H
1(
#485000
0(
#490000
b110000 H
1(
#495000
0(
#500000
b110001 H
1(
#505000
0(
#510000
b110010 H
1(
#515000
0(
#520000
b110011 H
1(
#525000
0(
#530000
b110100 H
1(
#535000
0(
#540000
b110101 H
1(
#545000
0(
#550000
b110110 H
1(
#555000
0(
#560000
b110111 H
1(
#565000
0(
#570000
b111000 H
1(
#575000
0(
#580000
b111001 H
1(
#585000
0(
#590000
b111010 H
1(
#595000
0(
#600000
b111011 H
1(
#605000
0(
#610000
b111100 H
1(
#615000
0(
#620000
b111101 H
1(
#625000
0(
#630000
b111110 H
1(
#635000
0(
#640000
b111111 H
1(
#645000
0(
#650000
b1000000 H
1(
#655000
0(
#660000
b1000001 H
1(
#665000
0(
#670000
b1000010 H
1(
#675000
0(
#680000
b1000011 H
1(
#685000
0(
#690000
b1000100 H
1(
#695000
0(
#700000
b1000101 H
1(
#705000
0(
#710000
b1000110 H
1(
#715000
0(
#720000
b1000111 H
1(
#725000
0(
#730000
b1001000 H
1(
#735000
0(
#740000
b1001001 H
1(
#745000
0(
#750000
b1001010 H
1(
#755000
0(
#760000
b1001011 H
1(
#765000
0(
#770000
b1001100 H
1(
#775000
0(
#780000
b1001101 H
1(
#785000
0(
#790000
b1001110 H
1(
#795000
0(
#800000
b1001111 H
1(
#805000
0(
#810000
b1010000 H
1(
#815000
0(
#820000
b1010001 H
1(
#825000
0(
#830000
b1010010 H
1(
#835000
0(
#840000
b1010011 H
1(
#845000
0(
#850000
b1010100 H
1(
#855000
0(
#860000
b1010101 H
1(
#865000
0(
#870000
b1010110 H
1(
#875000
0(
#880000
b1010111 H
1(
#885000
0(
#890000
b1011000 H
1(
#895000
0(
#900000
b1011001 H
1(
#905000
0(
#910000
b1011010 H
1(
#915000
0(
#920000
b1011011 H
1(
#925000
0(
#930000
b1011100 H
1(
#935000
0(
#940000
b1011101 H
1(
#945000
0(
#950000
b1011110 H
1(
#955000
0(
#960000
b1011111 H
1(
#965000
0(
#970000
b1100000 H
1(
#975000
0(
#980000
b1100001 H
1(
#985000
0(
#990000
b1100010 H
1(
#995000
0(
#1000000
b1100011 H
1(
#1005000
0(
#1010000
14
b1100100 H
1(
#1015000
0(
#1020000
04
b0 H
1(
#1025000
0(
#1030000
1#
b1 H
1(
#1035000
0(
#1040000
b10 H
1(
#1045000
0(
#1050000
b11 H
1(
#1055000
0(
#1060000
b100 H
1(
#1065000
0(
#1070000
b101 H
1(
#1075000
0(
#1080000
b110 H
1(
#1085000
0(
#1090000
b111 H
1(
#1095000
0(
#1100000
b1000 H
1(
#1105000
0(
#1110000
b1001 H
1(
#1115000
0(
#1120000
b1010 H
1(
#1125000
0(
#1130000
b1011 H
1(
#1135000
0(
#1140000
b1100 H
1(
#1145000
0(
#1150000
b1101 H
1(
#1155000
0(
#1160000
b1110 H
1(
#1165000
0(
#1170000
b1111 H
1(
#1175000
0(
#1180000
b10000 H
1(
#1185000
0(
#1190000
b10001 H
1(
#1195000
0(
#1200000
b10010 H
1(
#1205000
0(
#1210000
b10011 H
1(
#1215000
0(
#1220000
b10100 H
1(
#1225000
0(
#1230000
b10101 H
1(
#1235000
0(
#1240000
b10110 H
1(
#1245000
0(
#1250000
b10111 H
1(
#1255000
0(
#1260000
b11000 H
1(
#1265000
0(
#1270000
b11001 H
1(
#1275000
0(
#1280000
0#
b11010 H
1(
#1285000
0(
#1290000
b11011 H
1(
#1295000
0(
#1300000
b11100 H
1(
#1305000
0(
#1310000
b11101 H
1(
#1315000
0(
#1320000
b11110 H
1(
#1325000
0(
#1330000
b11111 H
1(
#1335000
0(
#1340000
b100000 H
1(
#1345000
0(
#1350000
b100001 H
1(
#1355000
0(
#1360000
b100010 H
1(
#1365000
0(
#1370000
b100011 H
1(
#1375000
0(
#1380000
b100100 H
1(
#1385000
0(
#1390000
b100101 H
1(
#1395000
0(
#1400000
b100110 H
1(
#1405000
0(
#1410000
b100111 H
1(
#1415000
0(
#1420000
b101000 H
1(
#1425000
0(
#1430000
b101001 H
1(
#1435000
0(
#1440000
b101010 H
1(
#1445000
0(
#1450000
b101011 H
1(
#1455000
0(
#1460000
b101100 H
1(
#1465000
0(
#1470000
b101101 H
1(
#1475000
0(
#1480000
b101110 H
1(
#1485000
0(
#1490000
b101111 H
1(
#1495000
0(
#1500000
b110000 H
1(
#1505000
0(
#1510000
b110001 H
1(
#1515000
0(
#1520000
b110010 H
1(
#1525000
0(
#1530000
b110011 H
1(
#1535000
0(
#1540000
b110100 H
1(
#1545000
0(
#1550000
b110101 H
1(
#1555000
0(
#1560000
b110110 H
1(
#1565000
0(
#1570000
b110111 H
1(
#1575000
0(
#1580000
b111000 H
1(
#1585000
0(
#1590000
b111001 H
1(
#1595000
0(
#1600000
b111010 H
1(
#1605000
0(
#1610000
b111011 H
1(
#1615000
0(
#1620000
b111100 H
1(
#1625000
0(
#1630000
b111101 H
1(
#1635000
0(
#1640000
b111110 H
1(
#1645000
0(
#1650000
b111111 H
1(
#1655000
0(
#1660000
b1000000 H
1(
#1665000
0(
#1670000
b1000001 H
1(
#1675000
0(
#1680000
b1000010 H
1(
#1685000
0(
#1690000
b1000011 H
1(
#1695000
0(
#1700000
b1000100 H
1(
#1705000
0(
#1710000
b1000101 H
1(
#1715000
0(
#1720000
b1000110 H
1(
#1725000
0(
#1730000
b1000111 H
1(
#1735000
0(
#1740000
b1001000 H
1(
#1745000
0(
#1750000
b1001001 H
1(
#1755000
0(
#1760000
b1001010 H
1(
#1765000
0(
#1770000
b1001011 H
1(
#1775000
0(
#1780000
b1001100 H
1(
#1785000
0(
#1790000
b1001101 H
1(
#1795000
0(
#1800000
b1001110 H
1(
#1805000
0(
#1810000
b1001111 H
1(
#1815000
0(
#1820000
b1010000 H
1(
#1825000
0(
#1830000
b1010001 H
1(
#1835000
0(
#1840000
b1010010 H
1(
#1845000
0(
#1850000
b1010011 H
1(
#1855000
0(
#1860000
b1010100 H
1(
#1865000
0(
#1870000
b1010101 H
1(
#1875000
0(
#1880000
b1010110 H
1(
#1885000
0(
#1890000
b1010111 H
1(
#1895000
0(
#1900000
b1011000 H
1(
#1905000
0(
#1910000
b1011001 H
1(
#1915000
0(
#1920000
b1011010 H
1(
#1925000
0(
#1930000
b1011011 H
1(
#1935000
0(
#1940000
b1011100 H
1(
#1945000
0(
#1950000
b1011101 H
1(
#1955000
0(
#1960000
b1011110 H
1(
#1965000
0(
#1970000
b1011111 H
1(
#1975000
0(
#1980000
b1100000 H
1(
#1985000
0(
#1990000
b1100001 H
1(
#1995000
0(
#2000000
b1100010 H
1(
#2005000
0(
#2010000
b1100011 H
1(
#2015000
0(
#2020000
14
b1100100 H
1(
#2025000
0(
#2030000
04
b0 H
1(
#2035000
0(
#2040000
1#
b1 H
1(
#2045000
0(
#2050000
b10 H
1(
#2055000
0(
#2060000
b11 H
1(
#2065000
0(
#2070000
b100 H
1(
#2075000
0(
#2080000
b101 H
1(
#2085000
0(
#2090000
b110 H
1(
#2095000
0(
#2100000
b111 H
1(
#2105000
0(
#2110000
b1000 H
1(
#2115000
0(
#2120000
b1001 H
1(
#2125000
0(
#2130000
b1010 H
1(
#2135000
0(
#2140000
b1011 H
1(
#2145000
0(
#2150000
b1100 H
1(
#2155000
0(
#2160000
b1101 H
1(
#2165000
0(
#2170000
b1110 H
1(
#2175000
0(
#2180000
b1111 H
1(
#2185000
0(
#2190000
b10000 H
1(
#2195000
0(
#2200000
b10001 H
1(
#2205000
0(
#2210000
b10010 H
1(
#2215000
0(
#2220000
b10011 H
1(
#2225000
0(
#2230000
b10100 H
1(
#2235000
0(
#2240000
b10101 H
1(
#2245000
0(
#2250000
b10110 H
1(
#2255000
0(
#2260000
b10111 H
1(
#2265000
0(
#2270000
b11000 H
1(
#2275000
0(
#2280000
b11001 H
1(
#2285000
0(
#2290000
0#
b11010 H
1(
#2295000
0(
#2300000
b11011 H
1(
#2305000
0(
#2310000
b11100 H
1(
#2315000
0(
#2320000
b11101 H
1(
#2325000
0(
#2330000
b11110 H
1(
#2335000
0(
#2340000
b11111 H
1(
#2345000
0(
#2350000
b100000 H
1(
#2355000
0(
#2360000
b100001 H
1(
#2365000
0(
#2370000
b100010 H
1(
#2375000
0(
#2380000
b100011 H
1(
#2385000
0(
#2390000
b100100 H
1(
#2395000
0(
#2400000
b100101 H
1(
#2405000
0(
#2410000
b100110 H
1(
#2415000
0(
#2420000
b100111 H
1(
#2425000
0(
#2430000
b101000 H
1(
#2435000
0(
#2440000
b101001 H
1(
#2445000
0(
#2450000
b101010 H
1(
#2455000
0(
#2460000
b101011 H
1(
#2465000
0(
#2470000
b101100 H
1(
#2475000
0(
#2480000
b101101 H
1(
#2485000
0(
#2490000
b101110 H
1(
#2495000
0(
#2500000
b101111 H
1(
#2505000
0(
#2510000
b110000 H
1(
#2515000
0(
#2520000
b110001 H
1(
#2525000
0(
#2530000
b110010 H
1(
#2535000
0(
#2540000
b110011 H
1(
#2545000
0(
#2550000
b110100 H
1(
#2555000
0(
#2560000
b110101 H
1(
#2565000
0(
#2570000
b110110 H
1(
#2575000
0(
#2580000
b110111 H
1(
#2585000
0(
#2590000
b111000 H
1(
#2595000
0(
#2600000
b111001 H
1(
#2605000
0(
#2610000
b111010 H
1(
#2615000
0(
#2620000
b111011 H
1(
#2625000
0(
#2630000
b111100 H
1(
#2635000
0(
#2640000
b111101 H
1(
#2645000
0(
#2650000
b111110 H
1(
#2655000
0(
#2660000
b111111 H
1(
#2665000
0(
#2670000
b1000000 H
1(
#2675000
0(
#2680000
b1000001 H
1(
#2685000
0(
#2690000
b1000010 H
1(
#2695000
0(
#2700000
b1000011 H
1(
#2705000
0(
#2710000
b1000100 H
1(
#2715000
0(
#2720000
b1000101 H
1(
#2725000
0(
#2730000
b1000110 H
1(
#2735000
0(
#2740000
b1000111 H
1(
#2745000
0(
#2750000
b1001000 H
1(
#2755000
0(
#2760000
b1001001 H
1(
#2765000
0(
#2770000
b1001010 H
1(
#2775000
0(
#2780000
b1001011 H
1(
#2785000
0(
#2790000
b1001100 H
1(
#2795000
0(
#2800000
b1001101 H
1(
#2805000
0(
#2810000
b1001110 H
1(
#2815000
0(
#2820000
b1001111 H
1(
#2825000
0(
#2830000
b1010000 H
1(
#2835000
0(
#2840000
b1010001 H
1(
#2845000
0(
#2850000
b1010010 H
1(
#2855000
0(
#2860000
b1010011 H
1(
#2865000
0(
#2870000
b1010100 H
1(
#2875000
0(
#2880000
b1010101 H
1(
#2885000
0(
#2890000
b1010110 H
1(
#2895000
0(
#2900000
b1010111 H
1(
#2905000
0(
#2910000
b1011000 H
1(
#2915000
0(
#2920000
b1011001 H
1(
#2925000
0(
#2930000
b1011010 H
1(
#2935000
0(
#2940000
b1011011 H
1(
#2945000
0(
#2950000
b1011100 H
1(
#2955000
0(
#2960000
b1011101 H
1(
#2965000
0(
#2970000
b1011110 H
1(
#2975000
0(
#2980000
b1011111 H
1(
#2985000
0(
#2990000
b1100000 H
1(
#2995000
0(
#3000000
b1100001 H
1(
#3005000
0(
#3010000
b1100010 H
1(
#3015000
0(
#3020000
b1100011 H
1(
#3025000
0(
#3030000
14
b1100100 H
1(
#3035000
0(
#3040000
04
b0 H
1(
#3045000
0(
#3050000
1#
b1 H
1(
#3055000
0(
#3060000
b10 H
1(
#3065000
0(
#3070000
b11 H
1(
#3075000
0(
#3080000
b100 H
1(
#3085000
0(
#3090000
b101 H
1(
#3095000
0(
#3100000
b110 H
1(
#3105000
0(
#3110000
b111 H
1(
#3115000
0(
#3120000
b1000 H
1(
#3125000
0(
#3130000
b1001 H
1(
#3135000
0(
